emoji/__init__.py
emoji/_python2.py
emoji/_unicode_characters.py
emoji/models.py
emoji/settings.py
emoji/tests.py
emoji/urls.py
emoji/views.py
emoji/static/emoji/img/+1.png
emoji/static/emoji/img/-1.png
emoji/static/emoji/img/100.png
emoji/static/emoji/img/1234.png
emoji/static/emoji/img/8ball.png
emoji/static/emoji/img/a.png
emoji/static/emoji/img/ab.png
emoji/static/emoji/img/abc.png
emoji/static/emoji/img/abcd.png
emoji/static/emoji/img/accept.png
emoji/static/emoji/img/aerial_tramway.png
emoji/static/emoji/img/airplane.png
emoji/static/emoji/img/alarm_clock.png
emoji/static/emoji/img/alien.png
emoji/static/emoji/img/ambulance.png
emoji/static/emoji/img/anchor.png
emoji/static/emoji/img/angel.png
emoji/static/emoji/img/anger.png
emoji/static/emoji/img/angry.png
emoji/static/emoji/img/anguished.png
emoji/static/emoji/img/ant.png
emoji/static/emoji/img/apple.png
emoji/static/emoji/img/aquarius.png
emoji/static/emoji/img/aries.png
emoji/static/emoji/img/arrow_backward.png
emoji/static/emoji/img/arrow_double_down.png
emoji/static/emoji/img/arrow_double_up.png
emoji/static/emoji/img/arrow_down.png
emoji/static/emoji/img/arrow_down_small.png
emoji/static/emoji/img/arrow_forward.png
emoji/static/emoji/img/arrow_heading_down.png
emoji/static/emoji/img/arrow_heading_up.png
emoji/static/emoji/img/arrow_left.png
emoji/static/emoji/img/arrow_lower_left.png
emoji/static/emoji/img/arrow_lower_right.png
emoji/static/emoji/img/arrow_right.png
emoji/static/emoji/img/arrow_right_hook.png
emoji/static/emoji/img/arrow_up.png
emoji/static/emoji/img/arrow_up_down.png
emoji/static/emoji/img/arrow_up_small.png
emoji/static/emoji/img/arrow_upper_left.png
emoji/static/emoji/img/arrow_upper_right.png
emoji/static/emoji/img/arrows_clockwise.png
emoji/static/emoji/img/arrows_counterclockwise.png
emoji/static/emoji/img/art.png
emoji/static/emoji/img/articulated_lorry.png
emoji/static/emoji/img/astonished.png
emoji/static/emoji/img/athletic_shoe.png
emoji/static/emoji/img/atm.png
django_emoji-2.2.2.dist-info/AUTHORS
django_emoji-2.2.2.dist-info/LICENSE
django_emoji-2.2.2.dist-info/METADATA
django_emoji-2.2.2.dist-info/WHEEL
django_emoji-2.2.2.dist-info/top_level.txt
django_emoji-2.2.2.dist-info/RECORD
